vkit_collect_usage_information/__init__.py
vkit_collect_usage_information-22.2.0.dist-info/LICENSE
vkit_collect_usage_information-22.2.0.dist-info/METADATA
vkit_collect_usage_information-22.2.0.dist-info/WHEEL
vkit_collect_usage_information-22.2.0.dist-info/top_level.txt
vkit_collect_usage_information-22.2.0.dist-info/RECORD
