Metadata-Version: 2.1
Name: vkit-collect-usage-information
Version: 22.2.0
Summary: todo
Home-page: https://github.com/vkit-x/vkit-collect-usage-information
Author: Hunt Zhan
Author-email: huntzhan@vkit-x.com
License: Not open source
Platform: UNKNOWN
Requires-Python: <3.12,>=3.8.0
Provides-Extra: dev
Requires-Dist: build (>=0.2.1) ; extra == 'dev'
Requires-Dist: fireball (>=0.5.0) ; extra == 'dev'
Requires-Dist: flake8 (>=3.8.4) ; extra == 'dev'
Requires-Dist: iolite (>=22.1.0) ; extra == 'dev'
Requires-Dist: ipython (>=7.20.0) ; extra == 'dev'
Requires-Dist: pdbpp (>=0.10.2) ; extra == 'dev'
Requires-Dist: pdoc3 (>=0.9.2) ; extra == 'dev'
Requires-Dist: pytest-parallel (>=0.1.1) ; extra == 'dev'
Requires-Dist: pytest (>=6.1.2) ; extra == 'dev'
Requires-Dist: rope (>=0.18.0) ; extra == 'dev'
Requires-Dist: twine (>=3.2.0) ; extra == 'dev'
Requires-Dist: yapf (>=0.30.0) ; extra == 'dev'
